setup.py
landlord_ai.egg-info/PKG-INFO
landlord_ai.egg-info/SOURCES.txt
landlord_ai.egg-info/dependency_links.txt
landlord_ai.egg-info/not-zip-safe
landlord_ai.egg-info/top_level.txt
landlordai/game/__init__.py
landlordai/game/card.py
landlordai/game/deck.py
landlordai/game/landlord.py
landlordai/game/move.py
landlordai/game/player.py
landlordai/sim/__init__.py
landlordai/sim/examine_game.py
landlordai/sim/example_sim.py
landlordai/sim/game_stats.py
landlordai/sim/long_sim.py
landlordai/sim/profile_sim.py
landlordai/sim/simulate.py