Metadata-Version: 1.0
Name: landlord-ai
Version: 0.1.36
Summary: Landlord AI Core
Home-page: UNKNOWN
Author: UNKNOWN
Author-email: seokhohong02@gmail.com
License: GNU
Platform: UNKNOWN
